kineverse-2025.11.16.dist-info/licenses/LICENSE
kv_lite/__init__.py
kv_lite/exp_utils.py
kv_lite/graph.py
kv_lite/layouting.py
kv_lite/lie.py
kv_lite/math.py
kv_lite/model.py
kv_lite/ros_utils.py
kv_lite/spatial.py
kv_lite/splines.py
kv_lite/urdf_utils.py
kv_lite/visualization.py
kineverse-2025.11.16.dist-info/METADATA
kineverse-2025.11.16.dist-info/WHEEL
kineverse-2025.11.16.dist-info/top_level.txt
kineverse-2025.11.16.dist-info/RECORD
