Metadata-Version: 2.4
Name: kineverse
Version: 2025.11.16
Summary: Differentiable Kinematics Using Numpy and Casadi.
Author-email: Adrian Röfer <aroefer@cs.uni-freiburg.de>
License-Expression: BSD-3-Clause
Project-URL: Homepage, https://github.com/ARoefer/kv_lite
Project-URL: Issues, https://github.com/ARoefer/kv_lite/issues
Classifier: Programming Language :: Python :: 3
Classifier: Operating System :: OS Independent
Requires-Python: >=3.8
License-File: LICENSE
Requires-Dist: numpy>=1.26.4
Requires-Dist: casadi
Requires-Dist: networkx
Provides-Extra: ros
Requires-Dist: jinja2; extra == "ros"
Requires-Dist: scipy>=1.14.0; extra == "ros"
Provides-Extra: vis
Requires-Dist: pyvis; extra == "vis"
Provides-Extra: rai
Requires-Dist: robotic; extra == "rai"
Dynamic: license-file
